Workbook
Name g: PREMISSAS!$B$4
Name IR: PREMISSAS!$B$5
Name Multiplo: PREMISSAS!$B$2
Name WACC: PREMISSAS!$B$3

Sheet PREMISSAS
A1: Premissa | B1: Valor | C1: OBS
A2: Múltiplo EV/EBITDA | B2: 12.8 | C2: Mediana do Setor para Fast Food
A3: WACC (Custo de Capital) | B3: 0.07 | C3: Estimativa Conservadora
A4: Crescimento na Perpetuidade (g) | B4: 0.025 | C4: Próximo à inflação
A5: Alíquota de IR | B5: 0.21 | C5: Guidance da Empresa 2026
A6: EBITDA (2025) | B6: 14640 | C6: US$ 14 BI

Sheet MULTIPLOS
A1: EBITDA(FY2025) | B1: =PREMISSAS!B6 -> 14640 | C1: US$ 14,6 Bilhões
A2: Múltiplo EV/EBITDA | B2: =Multiplo -> 12.8 | C2: 12x
A3: Enterprise Value (EV) | B3: =B1*B2 -> 187392 | C3: US$ 187,4 Bilhões
A4: (-) Dívida Líquida | B4: 54040 | C4: US$ 54 Bilhões
A5: Equity Value | B5: =B3-B4 -> 133352 | C5: US$ 133 Bilhões
A6: Número de Ações | B6: 712 | C6: 712 milhões
A7: Valor por Ação (Múltiplos) | B7: =B5/B6 -> 187.29213 | C7: unitário

Sheet DCF
A1: FCF | B1: 7190 | C1: US$ 7,19 Bilhões
A2: WACC | B2: =WACC -> 0.07
A3: Crescimento (g) | B3: =g -> 0.025
A4: Valor Terminal (VT) | B4: =(B1*(1+B3)) / (B2-B3) -> 163772.22 | C4: US$ 163,7 Bilhões
A5: Enterprise Value (EV) | B5: =MULTIPLOS!B5 -> 133352
A6: (-) Dívida Líquida | B6: 54040 | C6: US$ 54 Bilhões
A7: Equity Value | B7: =B4-B6 -> 109732.22 | C7: US$ 109 Bilhões
A8: Número de Ações | B8: =MULTIPLOS!B6 -> 712 | C8: 712 milhões
A9: Valor da Ação (DCF) | B9: =B7/B8 -> 154.11829 | C9: US$ 154

Sheet SENSIBILIDADE
A1: g | B1: 0.02 | C1: =g -> 0.025 | D1: 0.03 | E1: 0.04
A2: WACC | B2: 0.06 | C2: 0.07 | D2: 0.08 | E2: 0.09
A3: Valor Terminal | B3: =(DCF!$B$1*(1+SENSIBILIDADE!B1))/(SENSIBILIDADE!B2-SENSIBILIDADE!B1) -> 183345 | C3: =(DCF!$B$1*(1+SENSIBILIDADE!C1))/(SENSIBILIDADE!C2-SENSIBILIDADE!C1) -> 163772.22 | D3: =(DCF!$B$1*(1+SENSIBILIDADE!D1))/(SENSIBILIDADE!D2-SENSIBILIDADE!D1) -> 148114 | E3: =(DCF!$B$1*(1+SENSIBILIDADE!E1))/(SENSIBILIDADE!E2-SENSIBILIDADE!E1) -> 149552
A4: =DCF!A9 -> Valor da Ação (DCF) | B4: =(B3-DCF!$B$6)/DCF!$B$8 -> 181.60815 | C4: =(C3-DCF!$B$6)/DCF!$B$8 -> 154.11829 | D4: =(D3-DCF!$B$6)/DCF!$B$8 -> 132.1264 | E4: =(E3-DCF!$B$6)/DCF!$B$8 -> 134.14607
